ekmmeters.py
ekmmeters-0.2.5.dist-info/LICENSE.txt
ekmmeters-0.2.5.dist-info/METADATA
ekmmeters-0.2.5.dist-info/WHEEL
ekmmeters-0.2.5.dist-info/top_level.txt
ekmmeters-0.2.5.dist-info/RECORD
