Metadata-Version: 2.1
Name: ekmmeters
Version: 0.2.5
Summary: Python API for V3 and V4 EKM Omnimeters
Home-page: https://github.com/ekmmetering/ekmmeters
Author: EKM Metering
Author-email: info@ekmmetering.com
License: MIT
Platform: UNKNOWN
Classifier: Development Status :: 5 - Production/Stable
Classifier: Intended Audience :: Developers
Classifier: License :: OSI Approved :: MIT License
Requires-Dist: OrderedDict (>=1.1)
Requires-Dist: pyserial (>=3.0.1)
